{
    "configurations": [
        {
            "name": "Native",
            "includePath": [
                "${workspaceFolder}/Development/Include"
            ],
            "defines": [],
            "compilerPath": "/usr/bin/g++",
            "cStandard": "gnu11",
            "cppStandard": "gnu++17",
            "intelliSenseMode": "${default}"
        },
        {
            "name": "Cortex-M4-STM32F407",
            "includePath": [
                "${workspaceFolder}/Development/Include"
            ],
            "defines": [
                "STM32F407xx",
                "EMBEDDED_PLATFORM"
            ],
            "compilerPath": "/Applications/ARM/bin/arm-none-eabi-g++",
            "cStandard": "gnu11",
            "cppStandard": "gnu++17",
            "intelliSenseMode": "${default}"
        }
    ],
    "version": 4
}